{
    "2": {
        "id": 2,
        "smis": "86010002",
        "percode": "110021",
        "name": "วัดหาดทรายแก้ว",
        "clean_name": "วัดหาดทรายแก้ว",
        "website": "https:\/\/www.wathadsaikaew.ac.th",
        "email": "",
        "logo": ""
    },
    "1": {
        "id": 1,
        "smis": "86010001",
        "percode": "110064",
        "name": "วัดขุนกระทิง",
        "clean_name": "วัดขุนกระทิง",
        "website": "http:\/\/www.watkhunkrating.ac.th",
        "email": "watkhunkrating149@gmail.com",
        "logo": ""
    },
    "3": {
        "id": 3,
        "smis": "86010004",
        "percode": "110065",
        "name": "บ้านในห้วย",
        "clean_name": "บ้านในห้วย",
        "website": "http:\/\/www.bnhs.ac.th",
        "email": "",
        "logo": ""
    },
    "4": {
        "id": 4,
        "smis": "86010006",
        "percode": "110061",
        "name": "ชุมชนบ้านถ้ำสิงห์",
        "clean_name": "ชุมชนบ้านถ้ำสิงห์",
        "website": "http:\/\/www.banthamschool.ac.th",
        "email": "",
        "logo": ""
    },
    "5": {
        "id": 5,
        "smis": "86010008",
        "percode": "110020",
        "name": "อนุบาลชุมพร",
        "clean_name": "อนุบาลชุมพร",
        "website": "https:\/\/www.abcp.ac.th",
        "email": "",
        "logo": ""
    },
    "6": {
        "id": 6,
        "smis": "86010009",
        "percode": "110013",
        "name": "วัดดอนทรายแก้ว",
        "clean_name": "วัดดอนทรายแก้ว",
        "website": "http:\/\/obec.go.th\/watdonsaikiew",
        "email": "",
        "logo": ""
    },
    "7": {
        "id": 7,
        "smis": "86010010",
        "percode": "110008",
        "name": "วัดพิชัยยาราม",
        "clean_name": "วัดพิชัยยาราม",
        "website": "http:\/\/www.watpichaiyaram.ac.th",
        "email": "",
        "logo": ""
    },
    "8": {
        "id": 8,
        "smis": "86010011",
        "percode": "110009",
        "name": "บ้านคอสน",
        "clean_name": "บ้านคอสน",
        "website": "http:\/\/www.bankohsonschool.ac.th",
        "email": "",
        "logo": ""
    },
    "9": {
        "id": 9,
        "smis": "86010013",
        "percode": "110007",
        "name": "บ้านบางคอย",
        "clean_name": "บ้านบางคอย",
        "website": "http:\/\/www.banbangkoischool.ac.th",
        "email": "",
        "logo": ""
    },
    "10": {
        "id": 10,
        "smis": "86010014",
        "percode": "110012",
        "name": "บ้านบางหลง",
        "clean_name": "บ้านบางหลง",
        "website": "http:\/\/www.banglong.ac.th",
        "email": "",
        "logo": ""
    },
    "11": {
        "id": 11,
        "smis": "86010015",
        "percode": "110054",
        "name": "บ้านช่องไทรราษฎร์พัฒนา",
        "clean_name": "บ้านช่องไทรราษฎร์พัฒนา",
        "website": "http:\/\/www.banchongsai.ac.th",
        "email": "",
        "logo": ""
    },
    "12": {
        "id": 12,
        "smis": "86010016",
        "percode": "110053",
        "name": "บ้านทุ่งหงษ์",
        "clean_name": "บ้านทุ่งหงษ์",
        "website": "http:\/\/www.banthunghong.ac.th",
        "email": "",
        "logo": ""
    },
    "13": {
        "id": 13,
        "smis": "86010017",
        "percode": "110060",
        "name": "บ้านเขาบ่อ",
        "clean_name": "บ้านเขาบ่อ",
        "website": "",
        "email": "",
        "logo": ""
    },
    "14": {
        "id": 14,
        "smis": "86010019",
        "percode": "110051",
        "name": "วัดดอนมะม่วง",
        "clean_name": "วัดดอนมะม่วง",
        "website": "http:\/\/www.waddonmamuang.ac.th",
        "email": "",
        "logo": ""
    },
    "15": {
        "id": 15,
        "smis": "86010020",
        "percode": "110052",
        "name": "วัดทุ่งคา",
        "clean_name": "วัดทุ่งคา",
        "website": "",
        "email": "",
        "logo": ""
    },
    "16": {
        "id": 16,
        "smis": "86010021",
        "percode": "110018",
        "name": "อนุบาลเมืองชุมพร(วัดสุบรรณนิมิตร)",
        "clean_name": "อนุบาลเมืองชุมพร(วัดสุบรรณนิมิตร)",
        "website": "http:\/\/www.wsbcpn.ac.th",
        "email": "",
        "logo": ""
    },
    "17": {
        "id": 17,
        "smis": "86010023",
        "percode": "110034",
        "name": "วัดหูรอ",
        "clean_name": "วัดหูรอ",
        "website": "http:\/\/www.whr.ac.th",
        "email": "",
        "logo": ""
    },
    "18": {
        "id": 18,
        "smis": "86010024",
        "percode": "110036",
        "name": "บ้านสามเสียม",
        "clean_name": "บ้านสามเสียม",
        "website": "http:\/\/www.bansamseamschool.ac.th",
        "email": "",
        "logo": ""
    },
    "19": {
        "id": 19,
        "smis": "86010025",
        "percode": "110035",
        "name": "ชุมชนบ้านนาชะอัง",
        "clean_name": "ชุมชนบ้านนาชะอัง",
        "website": "",
        "email": "",
        "logo": ""
    },
    "20": {
        "id": 20,
        "smis": "86010027",
        "percode": "110038",
        "name": "วัดนาทุ่ง",
        "clean_name": "วัดนาทุ่ง",
        "website": "http:\/\/www.watnathungcpn1.ac.th",
        "email": "",
        "logo": ""
    },
    "21": {
        "id": 21,
        "smis": "86010029",
        "percode": "110041",
        "name": "บ้านหนองเนียน",
        "clean_name": "บ้านหนองเนียน",
        "website": "http:\/\/www.bannongnean.ac.th",
        "email": "",
        "logo": ""
    },
    "22": {
        "id": 22,
        "smis": "86010030",
        "percode": "110045",
        "name": "วัดบางลึก",
        "clean_name": "วัดบางลึก",
        "website": "http:\/\/www.watbangluek.ac.th",
        "email": "",
        "logo": ""
    },
    "23": {
        "id": 23,
        "smis": "86010032",
        "percode": "110047",
        "name": "บ้านศาลาลอย",
        "clean_name": "บ้านศาลาลอย",
        "website": "http:\/\/www.bansalaloi.ac.th",
        "email": "",
        "logo": ""
    },
    "24": {
        "id": 24,
        "smis": "86010036",
        "percode": "110014",
        "name": "วัดคูขุด",
        "clean_name": "วัดคูขุด",
        "website": "http:\/\/www.watkhukud.ac.th",
        "email": "",
        "logo": ""
    },
    "25": {
        "id": 25,
        "smis": "86010037",
        "percode": "110015",
        "name": "บ้านดอนไทรงาม",
        "clean_name": "บ้านดอนไทรงาม",
        "website": "http:\/\/www.bandonsaingam.ac.th",
        "email": "",
        "logo": ""
    },
    "26": {
        "id": 26,
        "smis": "86010039",
        "percode": "110016",
        "name": "บ้านคอเตี้ย",
        "clean_name": "บ้านคอเตี้ย",
        "website": "http:\/\/www.bankhotia.ac.th",
        "email": "",
        "logo": ""
    },
    "27": {
        "id": 27,
        "smis": "86010040",
        "percode": "110017",
        "name": "วัดดอนรวบ",
        "clean_name": "วัดดอนรวบ",
        "website": "http:\/\/www.wdr.ac.th",
        "email": "donroub@wdr.ac.th",
        "logo": ""
    },
    "28": {
        "id": 28,
        "smis": "86010041",
        "percode": "110063",
        "name": "บ้านเขาวง",
        "clean_name": "บ้านเขาวง",
        "website": "http:\/\/www.bankhaowong.ac.th",
        "email": "",
        "logo": ""
    },
    "29": {
        "id": 29,
        "smis": "86010042",
        "percode": "110023",
        "name": "บ้านท่ามะปริง",
        "clean_name": "บ้านท่ามะปริง",
        "website": "http:\/\/www.banthamapring.com",
        "email": "",
        "logo": ""
    },
    "30": {
        "id": 30,
        "smis": "86010043",
        "percode": "110005",
        "name": "วัดหัวกรูด",
        "clean_name": "วัดหัวกรูด",
        "website": "http:\/\/www.wathuakrudschool.ac.th",
        "email": "",
        "logo": ""
    },
    "73": {
        "id": 73,
        "smis": "86010102",
        "percode": "110108",
        "name": "บ้านร้านตัดผม",
        "clean_name": "บ้านร้านตัดผม",
        "website": "http:\/\/www.banrantadphom.ac.th",
        "email": "",
        "logo": ""
    },
    "31": {
        "id": 31,
        "smis": "86010044",
        "percode": "110001",
        "name": "บ้านปากน้ำ(เผดิมจีนนาวาสงเคราะห์)",
        "clean_name": "บ้านปากน้ำ(เผดิมจีนนาวาสงเคราะห์)",
        "website": "",
        "email": "",
        "logo": ""
    },
    "32": {
        "id": 32,
        "smis": "86010045",
        "percode": "110002",
        "name": "บ้านหัวถนน",
        "clean_name": "บ้านหัวถนน",
        "website": "http:\/\/www.banhuathanon.ac.th",
        "email": "",
        "logo": ""
    },
    "33": {
        "id": 33,
        "smis": "86010046",
        "percode": "110003",
        "name": "บ้านหาดภราดรภาพ",
        "clean_name": "บ้านหาดภราดรภาพ",
        "website": "",
        "email": "",
        "logo": ""
    },
    "34": {
        "id": 34,
        "smis": "86010047",
        "percode": "110025",
        "name": "เมืองชุมพรบ้านเขาถล่ม",
        "clean_name": "เมืองชุมพรบ้านเขาถล่ม",
        "website": "http:\/\/www.muangchumphonschool.ac.th",
        "email": "",
        "logo": ""
    },
    "35": {
        "id": 35,
        "smis": "86010048",
        "percode": "110026",
        "name": "วัดดอนเมือง",
        "clean_name": "วัดดอนเมือง",
        "website": "http:\/\/www.watdonmuangschool.ac.th",
        "email": "",
        "logo": ""
    },
    "36": {
        "id": 36,
        "smis": "86010052",
        "percode": "110029",
        "name": "ไทยรัฐวิทยา 66(บ้านนาเนียน)",
        "clean_name": "ไทยรัฐวิทยา 66(บ้านนาเนียน)",
        "website": "http:\/\/www.thairathvittaya66.ac.th",
        "email": "",
        "logo": ""
    },
    "37": {
        "id": 37,
        "smis": "86010053",
        "percode": "110030",
        "name": "วัดน้อมถวาย",
        "clean_name": "วัดน้อมถวาย",
        "website": "http:\/\/www.watnomthawai.ac.th",
        "email": "",
        "logo": ""
    },
    "38": {
        "id": 38,
        "smis": "86010055",
        "percode": "110032",
        "name": "บ้านนาแซะ",
        "clean_name": "บ้านนาแซะ",
        "website": "http:\/\/www.bannasae.ac.th",
        "email": "",
        "logo": ""
    },
    "39": {
        "id": 39,
        "smis": "86010056",
        "percode": "110033",
        "name": "บ้านท่าไม้ลาย",
        "clean_name": "บ้านท่าไม้ลาย",
        "website": "",
        "email": "",
        "logo": ""
    },
    "40": {
        "id": 40,
        "smis": "86010059",
        "percode": "110056",
        "name": "วัดเชิงกระ",
        "clean_name": "วัดเชิงกระ",
        "website": "",
        "email": "",
        "logo": ""
    },
    "41": {
        "id": 41,
        "smis": "86010060",
        "percode": "110058",
        "name": "บ้านคลองสูบ",
        "clean_name": "บ้านคลองสูบ",
        "website": "http:\/\/www.banklongsoob.ac.th",
        "email": "",
        "logo": ""
    },
    "42": {
        "id": 42,
        "smis": "86010061",
        "percode": "110059",
        "name": "บ้านเขาชันโต๊ะ",
        "clean_name": "บ้านเขาชันโต๊ะ",
        "website": "http:\/\/www.khaochunto.ac.th",
        "email": "",
        "logo": ""
    },
    "43": {
        "id": 43,
        "smis": "86010062",
        "percode": "110067",
        "name": "บ้านเขายาวราษฎร์พัฒนา",
        "clean_name": "บ้านเขายาวราษฎร์พัฒนา",
        "website": "http:\/\/www.bankhaoyaoschool.ac.th",
        "email": "",
        "logo": ""
    },
    "44": {
        "id": 44,
        "smis": "86010063",
        "percode": "110004",
        "name": "บ้านหาดทรายรี",
        "clean_name": "บ้านหาดทรายรี",
        "website": "",
        "email": "",
        "logo": ""
    },
    "45": {
        "id": 45,
        "smis": "86010064",
        "percode": "110006",
        "name": "บ้านทุ่งมะขาม",
        "clean_name": "บ้านทุ่งมะขาม",
        "website": "http:\/\/www.thungmakham.ac.th",
        "email": "",
        "logo": ""
    },
    "46": {
        "id": 46,
        "smis": "86010066",
        "percode": "110042",
        "name": "ชุมชนวัดหาดพันไกร",
        "clean_name": "ชุมชนวัดหาดพันไกร",
        "website": "http:\/\/www.hadphankrai.ac.th",
        "email": "hadphankrai@gmail.com",
        "logo": ""
    },
    "47": {
        "id": 47,
        "smis": "86010068",
        "percode": "110073",
        "name": "บ้านใหม่พัฒนา",
        "clean_name": "บ้านใหม่พัฒนา",
        "website": "http:\/\/www.banmaipattana.ac.th",
        "email": "",
        "logo": ""
    },
    "48": {
        "id": 48,
        "smis": "86010069",
        "percode": "110074",
        "name": "ประชานิคม 2",
        "clean_name": "ประชานิคม 2",
        "website": "http:\/\/www.prachanikom2.siamvip.com",
        "email": "",
        "logo": ""
    },
    "49": {
        "id": 49,
        "smis": "86010070",
        "percode": "110282",
        "name": "บ้านท่าลานทอง",
        "clean_name": "บ้านท่าลานทอง",
        "website": "http:\/\/www.bantalantong.ac.th",
        "email": "",
        "logo": ""
    },
    "50": {
        "id": 50,
        "smis": "86010071",
        "percode": "110072",
        "name": "ชุมชนบ้านคุริง (มิตรภาพที่ 25)",
        "clean_name": "ชุมชนบ้านคุริง (มิตรภาพที่ 25)",
        "website": "http:\/\/www.chumchonbankuring25.ac.th",
        "email": "",
        "logo": ""
    },
    "51": {
        "id": 51,
        "smis": "86010072",
        "percode": "110084",
        "name": "บ้านแก่งเพกา",
        "clean_name": "บ้านแก่งเพกา",
        "website": "http:\/\/www.Kaengphekathaifasthost.com",
        "email": "",
        "logo": ""
    },
    "52": {
        "id": 52,
        "smis": "86010073",
        "percode": "110081",
        "name": "บ้านหาดหงส์",
        "clean_name": "บ้านหาดหงส์",
        "website": "http:\/\/www.banhadhong.ac.th",
        "email": "",
        "logo": ""
    },
    "53": {
        "id": 53,
        "smis": "86010075",
        "percode": "110078",
        "name": "บ้านเขาพาง",
        "clean_name": "บ้านเขาพาง",
        "website": "",
        "email": "",
        "logo": ""
    },
    "54": {
        "id": 54,
        "smis": "86010076",
        "percode": "110079",
        "name": "บ้านหนองเรือ",
        "clean_name": "บ้านหนองเรือ",
        "website": "http:\/\/www.bnrschool.ac.th",
        "email": "",
        "logo": ""
    },
    "55": {
        "id": 55,
        "smis": "86010077",
        "percode": "110080",
        "name": "บ้านหัวว่าว",
        "clean_name": "บ้านหัวว่าว",
        "website": "",
        "email": "",
        "logo": ""
    },
    "56": {
        "id": 56,
        "smis": "86010078",
        "percode": "110083",
        "name": "บ้านหาดส้มแป้น",
        "clean_name": "บ้านหาดส้มแป้น",
        "website": "http:\/\/www.banhadsompan.com",
        "email": "",
        "logo": ""
    },
    "57": {
        "id": 57,
        "smis": "86010079",
        "percode": "110085",
        "name": "อนุบาลท่าแซะ(บ้านท่าแซะ)",
        "clean_name": "อนุบาลท่าแซะ(บ้านท่าแซะ)",
        "website": "http:\/\/www.anubanthasae.ac.th",
        "email": "",
        "logo": ""
    },
    "58": {
        "id": 58,
        "smis": "86010080",
        "percode": "110089",
        "name": "ชุมชนประชานิคม",
        "clean_name": "ชุมชนประชานิคม",
        "website": "http:\/\/www.prachanikhom.ac.th",
        "email": "",
        "logo": ""
    },
    "59": {
        "id": 59,
        "smis": "86010083",
        "percode": "110087",
        "name": "ไทยรัฐวิทยา 77(บ้านเนินสันติ)",
        "clean_name": "ไทยรัฐวิทยา 77(บ้านเนินสันติ)",
        "website": "",
        "email": "",
        "logo": ""
    },
    "60": {
        "id": 60,
        "smis": "86010089",
        "percode": "110093",
        "name": "บ้านละมุ",
        "clean_name": "บ้านละมุ",
        "website": "",
        "email": "",
        "logo": ""
    },
    "61": {
        "id": 61,
        "smis": "86010090",
        "percode": "110096",
        "name": "บ้านดอนเคี่ยม",
        "clean_name": "บ้านดอนเคี่ยม",
        "website": "http:\/\/www.bandonkiem.com",
        "email": "",
        "logo": ""
    },
    "62": {
        "id": 62,
        "smis": "86010091",
        "percode": "110098",
        "name": "บ้านรับร่อ",
        "clean_name": "บ้านรับร่อ",
        "website": "http:\/\/www.banrubroschool.ac.th",
        "email": "",
        "logo": ""
    },
    "63": {
        "id": 63,
        "smis": "86010092",
        "percode": "110100",
        "name": "บ้านหาดใน",
        "clean_name": "บ้านหาดใน",
        "website": "http:\/\/www.banhadnaischool.ac.th",
        "email": "",
        "logo": ""
    },
    "64": {
        "id": 64,
        "smis": "86010093",
        "percode": "110283",
        "name": "บ้านบางไม้แก้วประชาสามัคคี",
        "clean_name": "บ้านบางไม้แก้วประชาสามัคคี",
        "website": "",
        "email": "",
        "logo": ""
    },
    "65": {
        "id": 65,
        "smis": "86010094",
        "percode": "110077",
        "name": "บ้านเหมืองทอง",
        "clean_name": "บ้านเหมืองทอง",
        "website": "",
        "email": "",
        "logo": ""
    },
    "66": {
        "id": 66,
        "smis": "86010095",
        "percode": "110103",
        "name": "บ้านคันธทรัพย์",
        "clean_name": "บ้านคันธทรัพย์",
        "website": "http:\/\/www.khansup.ac.th",
        "email": "",
        "logo": ""
    },
    "67": {
        "id": 67,
        "smis": "86010096",
        "percode": "110104",
        "name": "บ้านเนินทอง",
        "clean_name": "บ้านเนินทอง",
        "website": "",
        "email": "",
        "logo": ""
    },
    "68": {
        "id": 68,
        "smis": "86010097",
        "percode": "110109",
        "name": "บ้านสวนทรัพย์",
        "clean_name": "บ้านสวนทรัพย์",
        "website": "http:\/\/www.bansuansub.ac.th",
        "email": "",
        "logo": ""
    },
    "69": {
        "id": 69,
        "smis": "86010098",
        "percode": "110106",
        "name": "บ้านพรุตะเคียน",
        "clean_name": "บ้านพรุตะเคียน",
        "website": "http:\/\/www.banpruthakieanschool.ac.th",
        "email": "",
        "logo": ""
    },
    "70": {
        "id": 70,
        "smis": "86010099",
        "percode": "110105",
        "name": "บ้านใหม่สมบูรณ์",
        "clean_name": "บ้านใหม่สมบูรณ์",
        "website": "http:\/\/www.banmaisomboon.ac.th",
        "email": "",
        "logo": ""
    },
    "71": {
        "id": 71,
        "smis": "86010100",
        "percode": "110102",
        "name": "บ้านงาช้าง",
        "clean_name": "บ้านงาช้าง",
        "website": "",
        "email": "",
        "logo": ""
    },
    "72": {
        "id": 72,
        "smis": "86010101",
        "percode": "110107",
        "name": "ประชาพัฒนา",
        "clean_name": "ประชาพัฒนา",
        "website": "http:\/\/www.prachapat.ac.th",
        "email": "",
        "logo": ""
    },
    "74": {
        "id": 74,
        "smis": "86010103",
        "percode": "110111",
        "name": "บ้านทรายขาว",
        "clean_name": "บ้านทรายขาว",
        "website": "http:\/\/www.bansaikhow.ac.th",
        "email": "",
        "logo": ""
    },
    "75": {
        "id": 75,
        "smis": "86010104",
        "percode": "110076",
        "name": "บ้านธรรมเจริญ",
        "clean_name": "บ้านธรรมเจริญ",
        "website": "http:\/\/www.banthamjaroen.ac.th",
        "email": "",
        "logo": ""
    },
    "76": {
        "id": 76,
        "smis": "86010105",
        "percode": "110110",
        "name": "บ้านตาหงษ์",
        "clean_name": "บ้านตาหงษ์",
        "website": "http:\/\/www.bantahong.ac.th",
        "email": "",
        "logo": ""
    },
    "77": {
        "id": 77,
        "smis": "86010106",
        "percode": "110068",
        "name": "บ้านกลาง",
        "clean_name": "บ้านกลาง",
        "website": "",
        "email": "",
        "logo": ""
    },
    "78": {
        "id": 78,
        "smis": "86010107",
        "percode": "110069",
        "name": "บ้านบึงลัด",
        "clean_name": "บ้านบึงลัด",
        "website": "",
        "email": "",
        "logo": ""
    },
    "79": {
        "id": 79,
        "smis": "86010108",
        "percode": "110070",
        "name": "ประชานิคม 4",
        "clean_name": "ประชานิคม 4",
        "website": "http:\/\/www.prachanikhom4.ac.th",
        "email": "",
        "logo": ""
    },
    "80": {
        "id": 80,
        "smis": "86010109",
        "percode": "110071",
        "name": "บ้านยายไท",
        "clean_name": "บ้านยายไท",
        "website": "http:\/\/www.banyaithaischool.com",
        "email": "",
        "logo": ""
    },
    "81": {
        "id": 81,
        "smis": "86010110",
        "percode": "110099",
        "name": "บ้านหินแก้ว",
        "clean_name": "บ้านหินแก้ว",
        "website": "",
        "email": "",
        "logo": ""
    },
    "82": {
        "id": 82,
        "smis": "86010111",
        "percode": "110101",
        "name": "บ้านน้ำเย็น",
        "clean_name": "บ้านน้ำเย็น",
        "website": "http:\/\/www.bannumyen.ac.th",
        "email": "",
        "logo": ""
    },
    "83": {
        "id": 83,
        "smis": "86010112",
        "percode": "110097",
        "name": "บ้านจันทึง",
        "clean_name": "บ้านจันทึง",
        "website": "http:\/\/www.banjunthungcpn1.ac.th",
        "email": "",
        "logo": ""
    },
    "84": {
        "id": 84,
        "smis": "86010113",
        "percode": "110118",
        "name": "บ้านทรายแก้ว",
        "clean_name": "บ้านทรายแก้ว",
        "website": "http:\/\/www.bansaikaew.com",
        "email": "",
        "logo": ""
    },
    "85": {
        "id": 85,
        "smis": "86010115",
        "percode": "110121",
        "name": "ไทยรัฐวิทยา ๗๖ (บ้านพละ)",
        "clean_name": "ไทยรัฐวิทยา ๗๖ (บ้านพละ)",
        "website": "http:\/\/www.thairatwitthaya76.com",
        "email": "",
        "logo": ""
    },
    "86": {
        "id": 86,
        "smis": "86010118",
        "percode": "110124",
        "name": "บ้านไชยราช",
        "clean_name": "บ้านไชยราช",
        "website": "http:\/\/www.banchairachcpn1.ac.th",
        "email": "",
        "logo": ""
    },
    "87": {
        "id": 87,
        "smis": "86010119",
        "percode": "110128",
        "name": "บ้านวังช้าง",
        "clean_name": "บ้านวังช้าง",
        "website": "http:\/\/www.banwangchang.ac.th",
        "email": "",
        "logo": ""
    },
    "88": {
        "id": 88,
        "smis": "86010120",
        "percode": "110132",
        "name": "บ้านหินกบ",
        "clean_name": "บ้านหินกบ",
        "website": "http:\/\/www.banhinkob.ac.th",
        "email": "",
        "logo": ""
    },
    "89": {
        "id": 89,
        "smis": "86010121",
        "percode": "110130",
        "name": "บ้านบางจาก",
        "clean_name": "บ้านบางจาก",
        "website": "http:\/\/www.banbangjark.ac.th",
        "email": "banbangjark.school2@gmail.com",
        "logo": ""
    },
    "90": {
        "id": 90,
        "smis": "86010122",
        "percode": "110131",
        "name": "บ้านชุมโค",
        "clean_name": "บ้านชุมโค",
        "website": "http:\/\/www.banchumco.ac.th",
        "email": "chumcoschool2562@gmail.com",
        "logo": ""
    },
    "91": {
        "id": 91,
        "smis": "86010124",
        "percode": "110133",
        "name": "บ้านดอนทราย",
        "clean_name": "บ้านดอนทราย",
        "website": "http:\/\/www.bandonsai.ac.th",
        "email": "-",
        "logo": ""
    },
    "92": {
        "id": 92,
        "smis": "86010126",
        "percode": "110129",
        "name": "บ้านบ่ออิฐ",
        "clean_name": "บ้านบ่ออิฐ",
        "website": "http:\/\/www.banboit.ac.th",
        "email": "banborit2558@gmail.com",
        "logo": ""
    },
    "93": {
        "id": 93,
        "smis": "86010127",
        "percode": "110125",
        "name": "บ้านทุ่งเรี้ย",
        "clean_name": "บ้านทุ่งเรี้ย",
        "website": "http:\/\/www.banthungria.ac.th",
        "email": "Kwanplum@gmail.com",
        "logo": ""
    },
    "94": {
        "id": 94,
        "smis": "86010128",
        "percode": "110119",
        "name": "ชุมชนมาบอำมฤต",
        "clean_name": "ชุมชนมาบอำมฤต",
        "website": "http:\/\/www.mapammarit.com",
        "email": "mapammarit016@gmail.com",
        "logo": ""
    },
    "95": {
        "id": 95,
        "smis": "86010129",
        "percode": "110120",
        "name": "วัดดอนยาง",
        "clean_name": "วัดดอนยาง",
        "website": "http:\/\/www.watdonyang.ac.th",
        "email": "watdonyang.2562@gmail.com",
        "logo": ""
    },
    "96": {
        "id": 96,
        "smis": "86010130",
        "percode": "110123",
        "name": "บ้านห้วยรากไม้",
        "clean_name": "บ้านห้วยรากไม้",
        "website": "http:\/\/www.banhuairakmai.ac.th",
        "email": "bhrmschool@gmail.com",
        "logo": ""
    },
    "97": {
        "id": 97,
        "smis": "86010131",
        "percode": "110138",
        "name": "ชุมชนบ้านทะเลทรัพย์",
        "clean_name": "ชุมชนบ้านทะเลทรัพย์",
        "website": "data.bopp-obec.info\/web\/home.php?School_ID=1086110138",
        "email": "Talasupschool@hotmail.com",
        "logo": ""
    },
    "98": {
        "id": 98,
        "smis": "86010132",
        "percode": "110145",
        "name": "บ้านคอกม้า",
        "clean_name": "บ้านคอกม้า",
        "website": "http:\/\/www.bkms.site",
        "email": "bankhokma@gmail.com",
        "logo": ""
    },
    "99": {
        "id": 99,
        "smis": "86010133",
        "percode": "110135",
        "name": "อนุบาลปะทิว(บางสนพิพิธราษฏร์บำรุง)",
        "clean_name": "อนุบาลปะทิว(บางสนพิพิธราษฏร์บำรุง)",
        "website": "http:\/\/anubanpathiu.ac.th\/",
        "email": "thama2404@gmail.com",
        "logo": ""
    },
    "100": {
        "id": 100,
        "smis": "86010134",
        "percode": "110136",
        "name": "บ้านดอนตะเคียน",
        "clean_name": "บ้านดอนตะเคียน",
        "website": "data.bopp-obec.info\/web\/index_view.php?School_ID=1086110136&page=info",
        "email": "bandontakean@gmail.com",
        "logo": ""
    },
    "101": {
        "id": 101,
        "smis": "86010136",
        "percode": "110117",
        "name": "บ้านน้ำพุ",
        "clean_name": "บ้านน้ำพุ",
        "website": "http:\/\/www.bannampu.com",
        "email": "bannumpuschool@gmail.com",
        "logo": ""
    },
    "102": {
        "id": 102,
        "smis": "86010137",
        "percode": "110115",
        "name": "บ้านถ้ำธง",
        "clean_name": "บ้านถ้ำธง",
        "website": "http:\/\/www.banthamthong.com",
        "email": "banthamthongschool@gmail.com",
        "logo": ""
    },
    "103": {
        "id": 103,
        "smis": "86010139",
        "percode": "110112",
        "name": "บ้านปากคลอง",
        "clean_name": "บ้านปากคลอง",
        "website": "http:\/\/www.banpakklong.ac.th",
        "email": "narongrit.in@obec.moe.go.th",
        "logo": ""
    },
    "104": {
        "id": 104,
        "smis": "86010140",
        "percode": "110113",
        "name": "วัดบางแหวน",
        "clean_name": "วัดบางแหวน",
        "website": "http:\/\/watbangwaen.ac.th",
        "email": "lodchongthai@hotmail.com",
        "logo": ""
    },
    "105": {
        "id": 105,
        "smis": "86010142",
        "percode": "110140",
        "name": "ไทยรัฐวิทยา๗๘(วัดสามัคคีชัย)",
        "clean_name": "ไทยรัฐวิทยา๗๘(วัดสามัคคีชัย)",
        "website": "http:\/\/thairathwittaya78.ac.th",
        "email": "78thairath@gmail.com",
        "logo": ""
    },
    "106": {
        "id": 106,
        "smis": "86010143",
        "percode": "110141",
        "name": "อนุบาลบ้านเนินสำลี",
        "clean_name": "อนุบาลบ้านเนินสำลี",
        "website": "http:\/\/www.noensumleeschool.com",
        "email": "noensumlee@gmail.com",
        "logo": ""
    },
    "107": {
        "id": 107,
        "smis": "86010145",
        "percode": "110143",
        "name": "บ้านสะพลี(บางกอกโพสต์ศึกษา)",
        "clean_name": "บ้านสะพลี(บางกอกโพสต์ศึกษา)",
        "website": "http:\/\/www.bansapalischool.ac.th",
        "email": "bansapli_school@hotmail.com",
        "logo": ""
    },
    "7202": {
        "id": 7202,
        "smis": "86010000",
        "percode": "",
        "name": "สำนักงานเขตพื้นที่การศึกษาประถมศึกษาชุมพร เขต 1",
        "clean_name": "สำนักงานเขตพื้นที่การศึกษาประถมศึกษาชุมพร เขต 1",
        "website": "https:\/\/www.cpn1.go.th",
        "email": "",
        "logo": ""
    }
}